{
  "GET": [
    {
      "rules": [{
        "param": [{
          "hallo": "b"
        }]
      }],
      "header":[
        {
          "X-Bla": "Hallo"
        },
        {
          "z-bla": "z-bla"
        }
      ],
      "httpcode": 200,
      "latency": 2,
      "body": "Hallo Welt with hallo param is b"
    },{
      "rules": [{
        "param": [{
          "hallo": "*"
        }]
      }],
      "header":[
        {
          "X-Bla": "Hallo"
        },
        {
          "z-bla": "z-bla"
        }
      ],
      "httpcode": 200,
      "latency": 2,
      "body": "Hallo Welt with hallo * param"
    },
    {
      "header":[
        {
          "X-Bla": "Hallo"
        },
        {
          "z-bla": "z-bla"
        }
      ],
      "httpcode": 200,
      "latency": 5,
      "body": "Hallo Welt"
    }
  ]
}
